dyada/__init__.py
dyada/ancestrybranch.py
dyada/coordinates.py
dyada/descriptor.py
dyada/discretization.py
dyada/drawing.py
dyada/linearization.py
dyada/refinement.py
dyada/structure.py
dyada-0.0.6.dist-info/METADATA
dyada-0.0.6.dist-info/WHEEL
dyada-0.0.6.dist-info/licenses/LICENSE
dyada-0.0.6.dist-info/RECORD
