Metadata-Version: 2.4
Name: dyada
Version: 0.0.6
Dynamic: Author
Dynamic: Author-email
Summary: A Code for Memory-Saving Dyadic Adaptivity in Optimization and Simulation
License-File: LICENSE
Classifier: Programming Language :: Python :: 3
Requires-Python: >=3.10
Requires-Dist: bitarray
Requires-Dist: numpy
Provides-Extra: drawing
Requires-Dist: cmap; extra == 'drawing'
Provides-Extra: matplotlib
Requires-Dist: matplotlib; extra == 'matplotlib'
Provides-Extra: opengl
Requires-Dist: pyopengl; extra == 'opengl'
